file_search/__init__.py
file_search/main.py
file_search/cache/__init__.py
file_search/cache/content_cache.py
file_search/file_scanner/__init__.py
file_search/file_scanner/scanner.py
file_search/search/__init__.py
file_search/search/searcher.py
file_search/text_extractor/__init__.py
file_search/text_extractor/ocr_extractor.py
file_search/text_extractor/text_extractor.py
file_search/utils/__init__.py
DocuGoggles-0.3.1.dist-info/LICENSE
DocuGoggles-0.3.1.dist-info/METADATA
DocuGoggles-0.3.1.dist-info/WHEEL
DocuGoggles-0.3.1.dist-info/entry_points.txt
DocuGoggles-0.3.1.dist-info/top_level.txt
DocuGoggles-0.3.1.dist-info/RECORD
